flame/__init__.py
flame/_utils.py
flame/engine/__init__.py
flame/engine/context.py
flame/engine/engine.py
flame/engine/event.py
flame/engine/exception.py
flame/engine/phase.py
flame/engine/scope.py
flame/engine/utils.py
flame/handlers/__init__.py
flame/handlers/context_snapshoter.py
flame/handlers/handler.py
flame/handlers/time_estimater.py
flame/metrics/__init__.py
flame/metrics/accuracy_metric.py
flame/metrics/average_metric.py
flame/metrics/metric.py
flame/metrics/reduce_metric.py
flame/metrics/time_metric.py
flame/metrics/utils.py
flame/utils/__init__.py
flame/utils/utils.py
flame/utils/summary/__init__.py
flame/utils/summary/core.py
flame/utils/summary/layers.py
torch_flame-0.1.0.dist-info/LICENSE
torch_flame-0.1.0.dist-info/METADATA
torch_flame-0.1.0.dist-info/WHEEL
torch_flame-0.1.0.dist-info/top_level.txt
torch_flame-0.1.0.dist-info/RECORD
